{
    "id": "brewin-path-playground",
    "name": {
        "en": "Brewin Path Playground",
        "zh": "蒲魯賢徑遊樂場"
    },
    "coords": {
        "lat": 22.274668661265956,
        "lng": 114.15626723799944
    },
    "district": {
        "en": "Central & Western",
        "zh": "中西區"
    },
    "address": {
        "en": "Brewin Path, Mid Levels",
        "zh": "半山蒲魯賢徑"
    },
    "equipment": [
        {
            "type": "others",
            "images": ["other_1", "other_2", "other_3", "other_4"]
        }
    ],
    "park_images": [
        "overview_1",
        "https://www.lcsd.gov.hk/file_upload_clpss/leisure_facilities/en/common/images/facilities/facilitieslist/fitness/1459_1.jpg",
        "overview_2",
        "overview_3"
    ],
    "metrics": {
        "quality": null
    },
    "comment": ""
}
